{
    "num_results": 20,
    "watches": [
        {
            "id": 13980,
            "refnr": "CKPT3304",
            "name": "Planetarium ",
            "brand": {
                "id": 63,
                "name": "Christiaan van der Klaauw"
            },
            "family": {
                "id": 313,
                "name": "Astronomical Masterpieces"
            },
            "thumb": "https:\/\/watchbase.r.sizr.io\/watch\/md\/christiaan-van-der-klaauw\/astronomical-masterpieces\/ckpt3304-21.jpg",
            "updated": "2015-02-08"
        },
        {
            "id": 13981,
            "refnr": "CKPT3344",
            "name": "Planetarium ",
            "brand": {
                "id": 63,
                "name": "Christiaan van der Klaauw"
            },
            "family": {
                "id": 313,
                "name": "Astronomical Masterpieces"
            },
            "thumb": "https:\/\/watchbase.r.sizr.io\/watch\/md\/christiaan-van-der-klaauw\/astronomical-masterpieces\/ckpt3344-c7.jpg",
            "updated": "2015-02-09"
        },
        {
            "id": 13986,
            "refnr": "CKPT1124",
            "name": "Planetarium ",
            "brand": {
                "id": 63,
                "name": "Christiaan van der Klaauw"
            },
            "family": {
                "id": 313,
                "name": "Astronomical Masterpieces"
            },
            "thumb": "https:\/\/watchbase.r.sizr.io\/watch\/md\/christiaan-van-der-klaauw\/astronomical-masterpieces\/ckpt1124-f2.jpg",
            "updated": "2015-02-09"
        },
        {
            "id": 13987,
            "refnr": "CKPT7724",
            "name": "Planetarium ",
            "brand": {
                "id": 63,
                "name": "Christiaan van der Klaauw"
            },
            "family": {
                "id": 313,
                "name": "Astronomical Masterpieces"
            },
            "thumb": "https:\/\/watchbase.r.sizr.io\/watch\/md\/christiaan-van-der-klaauw\/astronomical-masterpieces\/ckpt7724-f4.jpg",
            "updated": "2015-02-09"
        },
        {
            "id": 13988,
            "refnr": "CKPT7824",
            "name": "Planetarium ",
            "brand": {
                "id": 63,
                "name": "Christiaan van der Klaauw"
            },
            "family": {
                "id": 313,
                "name": "Astronomical Masterpieces"
            },
            "thumb": "https:\/\/watchbase.r.sizr.io\/watch\/md\/christiaan-van-der-klaauw\/astronomical-masterpieces\/ckpt7824-de.jpg",
            "updated": "2015-02-09"
        },
        {
            "id": 13989,
            "refnr": "CKPT7705",
            "name": "Planetarium ",
            "brand": {
                "id": 63,
                "name": "Christiaan van der Klaauw"
            },
            "family": {
                "id": 313,
                "name": "Astronomical Masterpieces"
            },
            "thumb": "https:\/\/watchbase.r.sizr.io\/watch\/md\/christiaan-van-der-klaauw\/astronomical-masterpieces\/ckpt7705-71.jpg",
            "updated": "2015-02-08"
        },
        {
            "id": 13990,
            "refnr": "CKPT2225",
            "name": "Planetarium ",
            "brand": {
                "id": 63,
                "name": "Christiaan van der Klaauw"
            },
            "family": {
                "id": 313,
                "name": "Astronomical Masterpieces"
            },
            "thumb": "https:\/\/watchbase.r.sizr.io\/watch\/md\/christiaan-van-der-klaauw\/astronomical-masterpieces\/ckpt2225-9.jpg",
            "updated": "2015-02-08"
        },
        {
            "id": 13991,
            "refnr": "CKRJ3384",
            "name": "Real Moon Joure 40Y ",
            "brand": {
                "id": 63,
                "name": "Christiaan van der Klaauw"
            },
            "family": {
                "id": 313,
                "name": "Astronomical Masterpieces"
            },
            "thumb": "https:\/\/watchbase.r.sizr.io\/watch\/md\/christiaan-van-der-klaauw\/astronomical-masterpieces\/ckrj3384-cb.jpg",
            "updated": "2015-02-09"
        },
        {
            "id": 13992,
            "refnr": "CKRJ3344",
            "name": "Real Moon Joure",
            "brand": {
                "id": 63,
                "name": "Christiaan van der Klaauw"
            },
            "family": {
                "id": 313,
                "name": "Astronomical Masterpieces"
            },
            "thumb": "https:\/\/watchbase.r.sizr.io\/watch\/md\/christiaan-van-der-klaauw\/astronomical-masterpieces\/ckrj3344-a5.jpg",
            "updated": "2015-02-09"
        },
        {
            "id": 13993,
            "refnr": "CKRJ3366",
            "name": "Real Moon Joure",
            "brand": {
                "id": 63,
                "name": "Christiaan van der Klaauw"
            },
            "family": {
                "id": 313,
                "name": "Astronomical Masterpieces"
            },
            "thumb": "https:\/\/watchbase.r.sizr.io\/watch\/md\/christiaan-van-der-klaauw\/astronomical-masterpieces\/ckrj3366-2d.jpg",
            "updated": "2015-02-09"
        },
        {
            "id": 13994,
            "refnr": "CKRJ3355",
            "name": "Real Moon Joure",
            "brand": {
                "id": 63,
                "name": "Christiaan van der Klaauw"
            },
            "family": {
                "id": 313,
                "name": "Astronomical Masterpieces"
            },
            "thumb": "https:\/\/watchbase.r.sizr.io\/watch\/md\/christiaan-van-der-klaauw\/astronomical-masterpieces\/ckrj3355-fd.jpg",
            "updated": "2015-02-09"
        },
        {
            "id": 13995,
            "refnr": "CKRJ3335",
            "name": "Real Moon Joure",
            "brand": {
                "id": 63,
                "name": "Christiaan van der Klaauw"
            },
            "family": {
                "id": 313,
                "name": "Astronomical Masterpieces"
            },
            "thumb": "https:\/\/watchbase.r.sizr.io\/watch\/md\/christiaan-van-der-klaauw\/astronomical-masterpieces\/ckrj3335-34.jpg",
            "updated": "2015-02-09"
        },
        {
            "id": 13996,
            "refnr": "CKRJ3304",
            "name": "Real Moon Joure",
            "brand": {
                "id": 63,
                "name": "Christiaan van der Klaauw"
            },
            "family": {
                "id": 313,
                "name": "Astronomical Masterpieces"
            },
            "thumb": "https:\/\/watchbase.r.sizr.io\/watch\/md\/christiaan-van-der-klaauw\/astronomical-masterpieces\/ckrj3304-55.jpg",
            "updated": "2015-02-09"
        },
        {
            "id": 13997,
            "refnr": "CKRJ3394",
            "name": "Real Moon Joure",
            "brand": {
                "id": 63,
                "name": "Christiaan van der Klaauw"
            },
            "family": {
                "id": 313,
                "name": "Astronomical Masterpieces"
            },
            "thumb": "https:\/\/watchbase.r.sizr.io\/watch\/md\/christiaan-van-der-klaauw\/astronomical-masterpieces\/ckrj3394-75.jpg",
            "updated": "2015-02-09"
        },
        {
            "id": 13998,
            "refnr": "CVDK7382",
            "name": "Real Moon Joure",
            "brand": {
                "id": 63,
                "name": "Christiaan van der Klaauw"
            },
            "family": {
                "id": 313,
                "name": "Astronomical Masterpieces"
            },
            "thumb": "https:\/\/watchbase.r.sizr.io\/watch\/md\/christiaan-van-der-klaauw\/astronomical-masterpieces\/cvdk7382-65.jpg",
            "updated": "2015-02-09"
        },
        {
            "id": 13999,
            "refnr": "CKRJ7705",
            "name": "Real Moon Joure",
            "brand": {
                "id": 63,
                "name": "Christiaan van der Klaauw"
            },
            "family": {
                "id": 313,
                "name": "Astronomical Masterpieces"
            },
            "thumb": "https:\/\/watchbase.r.sizr.io\/watch\/md\/christiaan-van-der-klaauw\/astronomical-masterpieces\/ckrj7705-70.jpg",
            "updated": "2015-02-09"
        },
        {
            "id": 14000,
            "refnr": "CKRJ7724",
            "name": "Real Moon Joure",
            "brand": {
                "id": 63,
                "name": "Christiaan van der Klaauw"
            },
            "family": {
                "id": 313,
                "name": "Astronomical Masterpieces"
            },
            "thumb": "https:\/\/watchbase.r.sizr.io\/watch\/md\/christiaan-van-der-klaauw\/astronomical-masterpieces\/ckrj7724-d9.jpg",
            "updated": "2015-02-09"
        },
        {
            "id": 14001,
            "refnr": "CKRJ7824",
            "name": "Real Moon Joure",
            "brand": {
                "id": 63,
                "name": "Christiaan van der Klaauw"
            },
            "family": {
                "id": 313,
                "name": "Astronomical Masterpieces"
            },
            "thumb": "https:\/\/watchbase.r.sizr.io\/watch\/md\/christiaan-van-der-klaauw\/astronomical-masterpieces\/ckrj7824-e1.jpg",
            "updated": "2015-02-09"
        },
        {
            "id": 15365,
            "refnr": "CKRS3324",
            "name": "Real Moon Tides Steel",
            "brand": {
                "id": 63,
                "name": "Christiaan van der Klaauw"
            },
            "family": {
                "id": 313,
                "name": "Astronomical Masterpieces"
            },
            "thumb": "https:\/\/watchbase.r.sizr.io\/watch\/md\/christiaan-van-der-klaauw\/astronomical-masterpieces\/ckrs3324-df.png",
            "updated": "2015-03-21"
        },
        {
            "id": 15366,
            "refnr": "CKRS1124",
            "name": " Real Moon Tides Rose Gold",
            "brand": {
                "id": 63,
                "name": "Christiaan van der Klaauw"
            },
            "family": {
                "id": 313,
                "name": "Astronomical Masterpieces"
            },
            "thumb": "https:\/\/watchbase.r.sizr.io\/watch\/md\/christiaan-van-der-klaauw\/astronomical-masterpieces\/ckrs1124-63.png",
            "updated": "2015-03-21"
        }
    ]
}